karp_lex_types/__init__.py
karp_lex_types/alias_generators.py
karp_lex_types/py.typed
karp_lex_types/commands/__init__.py
karp_lex_types/commands/base.py
karp_lex_types/commands/entry_commands.py
karp_lex_types/commands/entry_repo_commands.py
karp_lex_types/commands/resource_commands.py
karp_lex_types/dtos/__init__.py
karp_lex_types/dtos/entry_dto.py
karp_lex_types/value_objects/__init__.py
karp_lex_types/value_objects/unique_id.py
karp_lex_types-0.7.3.dist-info/METADATA
karp_lex_types-0.7.3.dist-info/WHEEL
karp_lex_types-0.7.3.dist-info/licenses/LICENSE
karp_lex_types-0.7.3.dist-info/RECORD
