Metadata-Version: 2.3
Name: karp-lex-types
Version: 0.7.3
Summary: The types of karp-lex
Project-URL: Bug Tracker, https://github.com/spraakbanken/karp-lex-types/issues
Project-URL: homepage, https://spraakbanken.gu.se
Project-URL: repository, https://github.com/spraakbanken/karp-lex-types
Project-URL: documentation, https://github.com/spraakbanken/karp-lex-types
Author-email: Språkbanken Text <sb-info@svenska.gu.se>, Kristoffer Andersson <kristoffer.andersson@gu.se>
License: MIT
License-File: LICENSE
Requires-Python: >=3.10
Requires-Dist: pydantic>=2.5.3
Requires-Dist: ulid-py>=1.1.0
